atap_corpus_slicer/CorpusSlicer.py
atap_corpus_slicer/Operation.py
atap_corpus_slicer/__init__.py
atap_corpus_slicer-0.3.6.dist-info/LICENSE
atap_corpus_slicer-0.3.6.dist-info/METADATA
atap_corpus_slicer-0.3.6.dist-info/WHEEL
atap_corpus_slicer-0.3.6.dist-info/RECORD
